MANIFEST.in
README.md
setup.py
pycp2k/__init__.py
pycp2k/config.py
pycp2k/cp2k.py
pycp2k/inputparser.py
pycp2k/inputsection.py
pycp2k/utilities.py
pycp2k.egg-info/PKG-INFO
pycp2k.egg-info/SOURCES.txt
pycp2k.egg-info/dependency_links.txt
pycp2k.egg-info/requires.txt
pycp2k.egg-info/top_level.txt
pycp2k/classes/_CP2K_INPUT1.py
pycp2k/classes/__init__.py
pycp2k/classes/_aa_cuboidal1.py
pycp2k/classes/_aa_cuboidal2.py
pycp2k/classes/_aa_cuboidal3.py
pycp2k/classes/_aa_cylindrical1.py
pycp2k/classes/_aa_cylindrical2.py
pycp2k/classes/_aa_cylindrical3.py
pycp2k/classes/_aa_planar1.py
pycp2k/classes/_aa_planar2.py
pycp2k/classes/_aa_planar3.py
pycp2k/classes/_acc1.py
pycp2k/classes/_accepts1.py
pycp2k/classes/_acid_hydronium_distance1.py
pycp2k/classes/_acid_hydronium_distance2.py
pycp2k/classes/_acid_hydronium_distance3.py
pycp2k/classes/_acid_hydronium_distance4.py
pycp2k/classes/_acid_hydronium_shell1.py
pycp2k/classes/_acid_hydronium_shell2.py
pycp2k/classes/_acid_hydronium_shell3.py
pycp2k/classes/_acid_hydronium_shell4.py
pycp2k/classes/_action1.py
pycp2k/classes/_action2.py
pycp2k/classes/_active_space1.py
pycp2k/classes/_ad_langevin1.py
pycp2k/classes/_ad_langevin2.py
pycp2k/classes/_ad_langevin3.py
pycp2k/classes/_add_mm_charge1.py
pycp2k/classes/_add_mm_charge2.py
pycp2k/classes/_add_mm_charge3.py
pycp2k/classes/_adiabatic_dynamics1.py
pycp2k/classes/_adiabatic_rescaling1.py
pycp2k/classes/_adiabatic_rescaling2.py
pycp2k/classes/_adiabatic_rescaling3.py
pycp2k/classes/_adiabatic_rescaling4.py
pycp2k/classes/_adiabatic_rescaling5.py
pycp2k/classes/_admm1.py
pycp2k/classes/_admm_basis1.py
pycp2k/classes/_ae_basis1.py
pycp2k/classes/_alchemical_change1.py
pycp2k/classes/_almo_cta1.py
pycp2k/classes/_almo_eda_ct1.py
pycp2k/classes/_almo_optimizer_diis1.py
pycp2k/classes/_almo_optimizer_pcg1.py
pycp2k/classes/_almo_scf1.py
pycp2k/classes/_alpha1.py
pycp2k/classes/_analysis1.py
pycp2k/classes/_analyze_basis1.py
pycp2k/classes/_andreussi1.py
pycp2k/classes/_angle1.py
pycp2k/classes/_angle2.py
pycp2k/classes/_angle3.py
pycp2k/classes/_angle4.py
pycp2k/classes/_angle5.py
pycp2k/classes/_angle_plane_plane1.py
